{
"update_url": "https://clients2.google.com/service/update2/crx",
"container":["GOOGLE_SPREADSHEET","DOMAIN_INSTALLABLE"],"app":{"background":{"scripts":["background.js"]}},"api_console_project_id":"550322772297","container_info":{"post_install_tip":"Just click on the menu option to generate a report for a particular period. A report tab will be shown with all details included.","help_url":"https://docs.google.com/document/d/141CI07aB3S25arJnq0RUWhkhIsktLjsrYn43aJLMGPM/preview","report_issue_url":"http://www.g-workplace.com/contact","container_id":"Mj7wtsqYikgjMHRZAhu28En5e1Rv07Lsx","container_version":"45"},"manifest_version":2,"name":"Reports4Hangouts","description":"Generates a report for you as an administrator of all Hangouts user activity within your domain.\n","icons":{"16":"script-icon_16.png","128":"script-icon_128.png"},"version":"44"}