{
"update_url": "https://clients2.google.com/service/update2/crx",
"name":"MY PERFECT SMILE ;P | XXXTENTACION PURPLE-RED","version":"1.0","description":"You see me as a monster ... wait .. look into my world. TOP ART XXXTENTACION Theme FOR Chrome 2018. Resolution: 1920X1080PX HD 16:9","manifest_version":2,"theme":{"images":{"theme_frame":"images\/theme_frame.jpeg","theme_toolbar":"images\/theme_toolbar.jpeg","theme_tab_background":"images\/theme_tab_background.jpeg","theme_ntp_background":"images\/theme_ntp_background.jpeg"},"colors":{"frame":[201,19,60],"toolbar":[220,102,128],"tab_text":[0,0,0],"tab_background_text":[255,0,30],"bookmark_text":[0,0,0],"ntp_background":[255,255,255],"ntp_text":[248,231,28],"button_background":[148,0,18,0.9]},"tints":{"buttons":[0,0,1]},"properties":{"ntp_background_alignment":"left bottom","ntp_background_repeat":"repeat"}}}