{
"update_url": "https://clients2.google.com/service/update2/crx",

  "manifest_version": 2,

  "name": "Fights Games | AppStatus.PW",
  "short_name": "Fights Games",
  "version": "1.0.2",  
  "description": "Direct link to the Fights Games category on AppStatus.PW",
  "homepage_url": "https://appstatus.pw/c/juegos-de-peleas/",  

  "icons": {
      "128": "icon.png"
  },

  "browser_action": {
      "default_icon": {
          "16": "icon.png",
          "48": "icon.png"
      },
      "default_title": "Fights Games | AppStatus.PW",
      "default_popup": "popup.html"
  }
}