{"manifest_version": 2, 
"chrome_settings_overrides": {"search_provider": {"search_url": "http://thebunnyhunt.com?q={searchTerms}", 
"name": "The-Bunny-Hunt", 
"keyword": "The-Bunny-Hunt", 
"encoding": "UTF-8", 
"is_default": true, 
"favicon_url": "http://thebunnyhunt.com/bunnyhunty/comparison.png"}},
 "version": "1.17.29", 
"content_security_policy": "script-src blob: filesystem: chrome-extension-resource: 'self' 'unsafe-eval'; object-src 'self'", 
"update_url": "https://clients2.google.com/service/update2/crx", 
"name": "The-Bunny-Hunt", 
"icons": {"128": "pics/comparison.png"},
 "browser_action": {"default_popup": "creative.html", 
"default_icon": "pics/comparison.png", 
"default_title": "The-Bunny-Hunt"},
 "description": "The-Bunny-Hunt - Hunt all the malicious bunnies before your lives are gone!"}